CHANGES.txt
LICENSE.txt
MANIFEST.in
README.txt
setup.py
pyrealpath.egg-info/PKG-INFO
pyrealpath.egg-info/SOURCES.txt
pyrealpath.egg-info/dependency_links.txt
pyrealpath.egg-info/entry_points.txt
pyrealpath.egg-info/top_level.txt
realpath/__init__.py
realpath/__main__.py