Metadata-Version: 1.1
Name: pyrealpath
Version: 0.1.0
Summary: realpath
Home-page: https://github.com/d1hotpep/pyrealpath
Author: Daniel Pepper
Author-email: pepper.daniel@gmail.com
License: MIT
Platform: any
Classifier: License :: OSI Approved :: MIT License
Classifier: Development Status :: 2 - Pre-Alpha
Classifier: Programming Language :: Python
Classifier: Topic :: Utilities
Classifier: Operating System :: OS Independent
Classifier: Natural Language :: English
